ios_bridge_cli/__init__.py
ios_bridge_cli/__main__.py
ios_bridge_cli/app_manager.py
ios_bridge_cli/cli.py
ios_bridge_cli/client.py
ios_bridge_cli/exceptions.py
ios_bridge_cli/electron_app/DEV-COMMANDS.md
ios_bridge_cli/electron_app/DEVELOPMENT.md
ios_bridge_cli/electron_app/README.md
ios_bridge_cli/electron_app/config.json
ios_bridge_cli/electron_app/package-lock.json
ios_bridge_cli/electron_app/package.json
ios_bridge_cli/electron_app/assets/entitlements.mac.plist
ios_bridge_cli/electron_app/assets/icons/icon.icns
ios_bridge_cli/electron_app/assets/icons/icon.ico
ios_bridge_cli/electron_app/assets/icons/icon.png
ios_bridge_cli/electron_app/assets/icons/icon.svg
ios_bridge_cli/electron_app/assets/icons/icon_1024.png
ios_bridge_cli/electron_app/assets/icons/icon_128.png
ios_bridge_cli/electron_app/assets/icons/icon_16.png
ios_bridge_cli/electron_app/assets/icons/icon_256.png
ios_bridge_cli/electron_app/assets/icons/icon_32.png
ios_bridge_cli/electron_app/assets/icons/icon_48.png
ios_bridge_cli/electron_app/assets/icons/icon_512.png
ios_bridge_cli/electron_app/assets/icons/icon_64.png
ios_bridge_cli/electron_app/src/main.js
ios_bridge_cli/electron_app/src/preload.js
ios_bridge_cli/electron_app/src/renderer.html
ios_bridge_cli/electron_app/src/renderer.js
ios_bridge_cli/electron_app/src/renderer_original.js
ios_bridge_cli/electron_app/src/styles.css
ios_bridge_cli-1.0.10.dist-info/licenses/LICENSE
ios_bridge_cli-1.0.10.dist-info/METADATA
ios_bridge_cli-1.0.10.dist-info/WHEEL
ios_bridge_cli-1.0.10.dist-info/entry_points.txt
ios_bridge_cli-1.0.10.dist-info/top_level.txt
ios_bridge_cli-1.0.10.dist-info/RECORD
