Metadata-Version: 2.4
Name: ios-bridge-cli
Version: 1.0.10
Summary: Desktop streaming client for iOS Bridge simulator sessions with Electron app integration
Home-page: https://github.com/AutoFlowLabs/ios-bridge-cli
Author: iOS Bridge Team
Author-email: iOS Bridge Team <kukreja.him@gmail.com>
License: MIT
Project-URL: Homepage, https://github.com/AutoFlowLabs/ios-bridge
Project-URL: Bug Tracker, https://github.com/AutoFlowLabs/ios-bridge/issues
Keywords: ios,simulator,bridge,streaming,electron,desktop,mobile,testing
Classifier: Development Status :: 4 - Beta
Classifier: Intended Audience :: Developers
Classifier: License :: OSI Approved :: MIT License
Classifier: Programming Language :: Python :: 3
Classifier: Programming Language :: Python :: 3.8
Classifier: Programming Language :: Python :: 3.9
Classifier: Programming Language :: Python :: 3.10
Classifier: Programming Language :: Python :: 3.11
Classifier: Operating System :: MacOS :: MacOS X
Classifier: Operating System :: POSIX :: Linux
Classifier: Operating System :: Microsoft :: Windows
Classifier: Topic :: Software Development :: Testing
Classifier: Topic :: System :: Emulators
Classifier: Topic :: Utilities
Requires-Python: >=3.8
License-File: LICENSE
Requires-Dist: click>=8.0.0
Requires-Dist: requests>=2.25.0
Requires-Dist: websockets>=10.0
Requires-Dist: pillow>=8.0.0
Requires-Dist: psutil>=5.8.0
Requires-Dist: aiohttp>=3.8.0
Requires-Dist: packaging>=21.0
Requires-Dist: fastapi>=0.100.0
Requires-Dist: uvicorn>=0.23.0
Requires-Dist: pydantic>=2.0.0
Requires-Dist: starlette>=0.27.0
Requires-Dist: python-multipart>=0.0.6
Requires-Dist: opencv-python>=4.5.0
Requires-Dist: numpy>=1.21.0
Requires-Dist: av>=10.0.0
Requires-Dist: jinja2>=3.0.0
Requires-Dist: aiortc>=1.6.0
Provides-Extra: dev
Requires-Dist: pytest>=6.0; extra == "dev"
Requires-Dist: pytest-asyncio>=0.18.0; extra == "dev"
Requires-Dist: black>=22.0; extra == "dev"
Requires-Dist: flake8>=4.0; extra == "dev"
Requires-Dist: mypy>=0.900; extra == "dev"
Requires-Dist: build>=0.8.0; extra == "dev"
Requires-Dist: twine>=4.0.0; extra == "dev"
Provides-Extra: server
Requires-Dist: fb-idb>=1.1.0; extra == "server"
Dynamic: author
Dynamic: home-page
Dynamic: license-file
Dynamic: requires-python
